LICENSE
MANIFEST.in
README.md
setup.cfg
setup.py
allianceauth_imicusfat.egg-info/PKG-INFO
allianceauth_imicusfat.egg-info/SOURCES.txt
allianceauth_imicusfat.egg-info/dependency_links.txt
allianceauth_imicusfat.egg-info/requires.txt
allianceauth_imicusfat.egg-info/top_level.txt
imicusfat/__init__.py
imicusfat/admin.py
imicusfat/app_settings.py
imicusfat/apps.py
imicusfat/auth_hooks.py
imicusfat/constants.py
imicusfat/forms.py
imicusfat/models.py
imicusfat/permissions.py
imicusfat/providers.py
imicusfat/swagger.json
imicusfat/tasks.py
imicusfat/tests.py
imicusfat/urls.py
imicusfat/utils.py
imicusfat/views.py
imicusfat/management/commands/imicusfat_import_from_allianceauth_fat.py
imicusfat/management/commands/imicusfat_import_from_bfat.py
imicusfat/migrations/0001_0013_optimized_migrations.py
imicusfat/migrations/0001_initial.py
imicusfat/migrations/0002_auto_20201020_1159.py
imicusfat/migrations/0002_manualfat.py
imicusfat/migrations/0003_auto_20180911_0831.py
imicusfat/migrations/0003_auto_20201224_1110.py
imicusfat/migrations/0004_clickfatduration.py
imicusfat/migrations/0004_ifatlink_character.py
imicusfat/migrations/0005_auto_20200816_2042.py
imicusfat/migrations/0006_auto_20200820_2013.py
imicusfat/migrations/0007_auto_20200826_1537.py
imicusfat/migrations/0008_auto_20200912_1121.py
imicusfat/migrations/0009_ifatlink_is_esilink.py
imicusfat/migrations/0010_ifatlinktype_is_enabled.py
imicusfat/migrations/0011_auto_20201004_0936.py
imicusfat/migrations/0012_basic_module_access_permissions.py
imicusfat/migrations/0013_auto_20201019_1649.py
imicusfat/migrations/__init__.py
imicusfat/static/imicusfat/css/aa-bootstrap-fix.css
imicusfat/static/imicusfat/css/aa-bootstrap-fix.min.css
imicusfat/static/imicusfat/css/imicusfat.css
imicusfat/static/imicusfat/css/imicusfat.min.css
imicusfat/static/imicusfat/javascript/chart-js/Chart.min.js
imicusfat/static/imicusfat/libs/datatables/plugins/dataTables.rowGroup.min.js
imicusfat/static/imicusfat/libs/datatables/plugins/datetime.js
imicusfat/static/imicusfat/libs/datatables/plugins/datetime.min.js
imicusfat/static/imicusfat/libs/datatables/plugins/rowGroup.bootstrap.min.css
imicusfat/static/imicusfat/libs/datatables/plugins/rowGroup.dataTables.min.css
